{"date_crawled": "20220826", "item_name": "Botol oli samping rx king rxk rx special rxz", "url": "https://shopee.co.id/Botol-oli-samping-rx-king-rxk-rx-special-rxz-i.221601231.7562933435", "shopid": "221601231", "itemid": "7562933435", "model_itemid": "7562933435", "sale_price": 160000.0, "item_price": 160000.0, "high_price": 160000.0, "brand": "", "item_rating": 4.64, "item_rating_count": 11.0, "product group": "ENGINE OILS MOTOR CYCLES", "unique_name": "MCO", "country": "ID", "seller_name": "aziz2541", "seller_rating": 4.630872, "seller_follower_count": 1276, "shopee_verified": true, "is_preferred_plus_seller": false, "is_official_shop": false}