{"date_crawled": "20220826", "item_name": "Crangcase Block Kanan Kalter Mesin Kanan Tap Oli HONDA BEAT ESP SCOOPY ESP Original Copotan Motor", "url": "https://shopee.co.id/Crangcase-Block-Kanan-Kalter-Mesin-Kanan-Tap-Oli-HONDA-BEAT-ESP-SCOOPY-ESP-Original-Copotan-Motor-i.38643832.3379885150", "shopid": "38643832", "itemid": "3379885150", "model_itemid": "3379885150", "sale_price": 150900.0, "item_price": 150900.0, "high_price": 150900.0, "brand": "Honda", "item_rating": 4.0, "item_rating_count": 2.0, "product group": "ENGINE OILS MOTOR CYCLES", "unique_name": "MCO", "country": "ID", "seller_name": "anggaputra3", "seller_rating": 4.413075, "seller_follower_count": 4277, "shopee_verified": false, "is_preferred_plus_seller": false, "is_official_shop": false}