{"date_crawled": "20220826", "item_name": "Crankcase Blok Kanan Tap Oli Genio Beat K1A Scoopy K2F 11100-K0J-N00", "url": "https://shopee.co.id/Crankcase-Blok-Kanan-Tap-Oli-Genio-Beat-K1A-Scoopy-K2F-11100-K0J-N00-i.303059761.7373488597", "shopid": "303059761", "itemid": "7373488597", "model_itemid": "7373488597", "sale_price": 475000.0, "item_price": 475000.0, "high_price": 475000.0, "brand": "Honda", "item_rating": 4.5, "item_rating_count": 4.0, "product group": "ENGINE OILS MOTOR CYCLES", "unique_name": "MCO", "country": "ID", "seller_name": "yunishop78", "seller_rating": 4.823391, "seller_follower_count": 382, "shopee_verified": false, "is_preferred_plus_seller": false, "is_official_shop": false}