{"date_crawled": "20220826", "item_name": "OPPO Enco Buds [24H Battery Life, Low-Latency Gaming Mode, Bass-driven HD Sound] - OPPO Official Accessories [GRATIS WIRED EARPHONE]", "url": "https://shopee.co.id/OPPO-Enco-Buds-24H-Battery-Life-Low-Latency-Gaming-Mode-Bass-driven-HD-Sound-OPPO-Official-Accessories-GRATIS-WIRED-EARPHONE--i.777837683.20709098046", "shopid": "777837683", "itemid": "20709098046", "model_itemid": "20709098046", "sale_price": 549000.0, "item_price": 549000.0, "high_price": 549000.0, "brand": "", "item_rating": 5.0, "item_rating_count": 7.0, "product group": "HEADSETS", "unique_name": "HDS", "country": "ID", "seller_name": "oppoacc.id", "seller_rating": 4.866667, "seller_follower_count": 2789, "shopee_verified": false, "is_preferred_plus_seller": false, "is_official_shop": true}