{"date_crawled": "20220826", "item_name": "Robot Earphone Airbuds T10 Waterproof IPX4 Semi-In-Ear TWS True Wireless Stereo ORI- Garansi 1 Tahun", "url": "https://shopee.co.id/Robot-Earphone-Airbuds-T10-Waterproof-IPX4-Semi-In-Ear-TWS-True-Wireless-Stereo-ORI-Garansi-1-Tahun-i.11868085.11121113090", "shopid": "11868085", "itemid": "11121113090", "model_itemid": "11121113090", "sale_price": 209500.0, "item_price": 209500.0, "high_price": 209500.0, "brand": "", "item_rating": 4.77, "item_rating_count": 2420.0, "product group": "HEADSETS", "unique_name": "HDS", "country": "ID", "seller_name": "robotofficialshop.id", "seller_rating": 4.841167, "seller_follower_count": 1229924, "shopee_verified": false, "is_preferred_plus_seller": false, "is_official_shop": true}