{"date_crawled": "20220826", "item_name": "TWS Earphone Handsfree Bluetooth 5.1 HiFi Stereo Waterproof Earbuds Wireless Earphone Noise Cancel With Microphone Untuk Android IOS", "url": "https://shopee.co.id/TWS-Earphone-Handsfree-Bluetooth-5.1-HiFi-Stereo-Waterproof-Earbuds-Wireless-Earphone-Noise-Cancel-With-Microphone-Untuk-Android-IOS-i.587469532.16430553015", "shopid": "587469532", "itemid": "16430553015", "model_itemid": "16430553015", "sale_price": 159000.0, "item_price": 159000.0, "high_price": 169000.0, "brand": "", "item_rating": 4.77, "item_rating_count": 211.0, "product group": "HEADSETS", "unique_name": "HDS", "country": "ID", "seller_name": "xpokoofficialstore", "seller_rating": 4.766129, "seller_follower_count": 509, "shopee_verified": false, "is_preferred_plus_seller": false, "is_official_shop": false}