{"date_crawled": "20220826", "item_name": "pan blok oli dan paking ninja 250 fi lama atau z250 fi ori", "url": "https://shopee.co.id/pan-blok-oli-dan-paking-ninja-250-fi-lama-atau-z250-fi-ori-i.54273809.3751225220", "shopid": "54273809", "itemid": "3751225220", "model_itemid": "3751225220", "sale_price": 633000.0, "item_price": 633000.0, "high_price": 633000.0, "brand": "Kawasaki", "item_rating": 4.71, "item_rating_count": 7.0, "product group": "ENGINE OILS MOTOR CYCLES", "unique_name": "MCO", "country": "ID", "seller_name": "antonurochmat", "seller_rating": 4.78867, "seller_follower_count": 2385, "shopee_verified": true, "is_preferred_plus_seller": false, "is_official_shop": false}