{"date_crawled": "20220826", "item_name": "TEMPAT OLI SAMPING YAMAHA RX KING RXK RXZ VARIASI", "url": "https://shopee.co.id/TEMPAT-OLI-SAMPING-YAMAHA-RX-KING-RXK-RXZ-VARIASI-i.18729279.7824047467", "shopid": "18729279", "itemid": "7824047467", "model_itemid": "7824047467", "sale_price": 200000.0, "item_price": 200000.0, "high_price": 200000.0, "brand": "", "item_rating": 4.86, "item_rating_count": 14.0, "product group": "ENGINE OILS MOTOR CYCLES", "unique_name": "MCO", "country": "ID", "seller_name": "khoirunniam69", "seller_rating": 4.57068, "seller_follower_count": 4290, "shopee_verified": true, "is_preferred_plus_seller": false, "is_official_shop": false}