{"date_crawled": "20220826", "item_name": "POMPA OLI", "url": "https://shopee.co.id/POMPA-OLI-i.203237716.15986548620", "shopid": "203237716", "itemid": "15986548620", "model_itemid": "15986548620", "sale_price": 255000.0, "item_price": 255000.0, "high_price": 255000.0, "brand": "", "item_rating": 5.0, "item_rating_count": 2.0, "product group": "ENGINE OILS MOTOR CYCLES", "unique_name": "MCO", "country": "ID", "seller_name": "oversizegeser88", "seller_rating": 4.850806, "seller_follower_count": 2567, "shopee_verified": false, "is_preferred_plus_seller": false, "is_official_shop": false}