{"date_crawled": "20220826", "item_name": "ger pompa oli F1ZR gir pompa oli samping F1zr datar gigi pompa oli samping F1zr datar", "url": "https://shopee.co.id/ger-pompa-oli-F1ZR-gir-pompa-oli-samping-F1zr-datar-gigi-pompa-oli-samping-F1zr-datar-i.79342195.19507830988", "shopid": "79342195", "itemid": "19507830988", "model_itemid": "19507830988", "sale_price": 150000.0, "item_price": 150000.0, "high_price": 150000.0, "brand": "", "item_rating": 5.0, "item_rating_count": 4.0, "product group": "ENGINE OILS MOTOR CYCLES", "unique_name": "MCO", "country": "ID", "seller_name": "kriswantop", "seller_rating": 4.768229, "seller_follower_count": 535, "shopee_verified": true, "is_preferred_plus_seller": false, "is_official_shop": false}