{"date_crawled": "20220826", "item_name": "Sony HDR-CX405 HD Handycam Garansi Resmi Sony - Non Paket", "url": "https://shopee.co.id/Sony-HDR-CX405-HD-Handycam-Garansi-Resmi-Sony-Non-Paket-i.393484247.9732878742", "shopid": "393484247", "itemid": "9732878742", "model_itemid": "9732878742", "sale_price": 3399000.0, "item_price": 3399000.0, "high_price": 3399000.0, "brand": "Sony", "item_rating": 5.0, "item_rating_count": 3.0, "product group": "CAMCORDER", "unique_name": "CAM", "country": "ID", "seller_name": "planet_gadget", "seller_rating": 4.972222, "seller_follower_count": 12, "shopee_verified": false, "is_preferred_plus_seller": false, "is_official_shop": false}