{"date_crawled": "20220826", "item_name": "Anti Air IP67 Jam tangan anak telepon - anak Gps Digital Smartwatch anak Waterproof Kids Smart Watch", "url": "https://shopee.co.id/Anti-Air-IP67-Jam-tangan-anak-telepon-anak-Gps-Digital-Smartwatch-anak-Waterproof-Kids-Smart-Watch-i.609122900.16275066578", "shopid": "609122900", "itemid": "16275066578", "model_itemid": "16275066578", "sale_price": 150000.0, "item_price": 150000.0, "high_price": 150000.0, "brand": "", "item_rating": 4.3, "item_rating_count": 50.0, "product group": "CORE WEARABLES", "unique_name": "CWR", "country": "ID", "seller_name": "jnew.watch", "seller_rating": 4.77116, "seller_follower_count": 999, "shopee_verified": false, "is_preferred_plus_seller": false, "is_official_shop": false}