{"date_crawled": "20220826", "item_name": "Pompa Asi Silikon - Manual / Breast Pump Manual (FREE PACKING BUBBLE WRAP)", "url": "https://shopee.co.id/Pompa-Asi-Silikon-Manual-Breast-Pump-Manual-(FREE-PACKING-BUBBLE-WRAP)-i.94661762.9313722136", "shopid": "94661762", "itemid": "9313722136", "model_itemid": "9313722136", "sale_price": 26990.0, "item_price": 26990.0, "high_price": 26990.0, "brand": "Tidak Ada Merek", "item_rating": 4.85, "item_rating_count": 848.0, "product group": "BREAST FEEDING", "unique_name": "BFEED", "country": "ID", "seller_name": "lakulakuaja", "seller_rating": 4.830845, "seller_follower_count": 2356, "shopee_verified": true, "is_preferred_plus_seller": true, "is_official_shop": false}