{"date_crawled": "20220826", "item_name": "[TM] Pompa Asi Manual Bahan Silikon", "url": "https://shopee.co.id/-TM-Pompa-Asi-Manual-Bahan-Silikon-i.161125477.13524760225", "shopid": "161125477", "itemid": "13524760225", "model_itemid": "13524760225", "sale_price": 28990.0, "item_price": 28990.0, "high_price": 28990.0, "brand": "", "item_rating": 4.83, "item_rating_count": 160.0, "product group": "BREAST FEEDING", "unique_name": "BFEED", "country": "ID", "seller_name": "toserbamarket", "seller_rating": 4.802934, "seller_follower_count": 18301, "shopee_verified": true, "is_preferred_plus_seller": false, "is_official_shop": false}