{"date_crawled": "20220826", "item_name": "SONY HT-S40R 5.1ch Home Cinema with Wireless Rear Speakers Garansi Resmi Sony", "url": "https://shopee.co.id/SONY-HT-S40R-5.1ch-Home-Cinema-with-Wireless-Rear-Speakers-Garansi-Resmi-Sony-i.26350778.14974547222", "shopid": "26350778", "itemid": "14974547222", "model_itemid": "14974547222", "sale_price": 4399000.0, "item_price": 4399000.0, "high_price": 4399000.0, "brand": "", "item_rating": 5.0, "item_rating_count": 1.0, "product group": "AUDIO HOME SYS.", "unique_name": "AHS", "country": "ID", "seller_name": "andruarvinostore", "seller_rating": 4.938503, "seller_follower_count": 1851, "shopee_verified": true, "is_preferred_plus_seller": false, "is_official_shop": false}