{"date_crawled": "20220826", "item_name": "HOME THEATER POLYTRON - PHT 500 SR", "url": "https://shopee.co.id/HOME-THEATER-POLYTRON-PHT-500-SR-i.27486532.1547419583", "shopid": "27486532", "itemid": "1547419583", "model_itemid": "1547419583", "sale_price": 1564000.0, "item_price": 1564000.0, "high_price": 1564000.0, "brand": "Polytron", "item_rating": 5.0, "item_rating_count": 1.0, "product group": "AUDIO HOME SYS.", "unique_name": "AHS", "country": "ID", "seller_name": "sinarelektrik", "seller_rating": 4.844894, "seller_follower_count": 17374, "shopee_verified": true, "is_preferred_plus_seller": false, "is_official_shop": false}