[{"cat_0": "Computers & Accessories", "cat_1": "Desktop Computers", "cat_2": "Desktop PC", "modelid": 173687181308, "date_crawled": "20220826", "item_name": "COMPUTER PACKAGE INTEL CORE 2 DUO DELL 2GB 160GB HDD WITH 17 INCHES FREE HEADSET AND MOUSEPAD", "url": "https://shopee.ph/COMPUTER-PACKAGE-INTEL-CORE-2-DUO-DELL-2GB-160GB-HDD-WITH-17-INCHES-FREE-HEADSET-AND-MOUSEPAD-i.359393740.8598186694", "shopid": "359393740", "itemid": "8598186694", "model_itemid": "8598186694", "sale_price": 1999.0, "item_price": 1999.0, "high_price": 4899.0, "brand": "", "item_rating": 4.69, "item_rating_count": 118.0, "product group": "GAS WATER HEATERS", "unique_name": "GWH", "country": "ID", "seller_name": "t5corp", "seller_rating": 4.615909, "seller_follower_count": 6905, "shopee_verified": false, "is_preferred_plus_seller": false, "is_official_shop": false, "item_desc": "SPECIFICATION:\n\n\u2705Processor: EDEX X2-U4200 \n\u2705Ram: 2gb RAM \n\u2705Storage: 16gb HDD\n\u2705Chrome9 HD GPI\n\u270519\" LCD SQ White Monitor\n\u2705Keyboard & Mouse\n\u2705Mousepad\n\u2705Cords included\n\u27051 Month warranty store replacement\n\u2705SHOPEE LINK:", "orig_price": 0.0, "stock": 601, "historical_sold": 289, "sold": 25, "model_count": 12, "model_stock": 19, "model_name": "4GB WIFI WEBCAM RDY", "model_orig_price": 0.0, "model_sale_price": 3899.0, "final_price": 3899.0, "model_sold": 0, "total_model_sold": 0, "voucher_discount": 300.0, "model_contribution": 0.03161397670549085, "sales_units": 1, "warranty": "1 Month", "show_original_guarantee": false}, {"cat_0": "Computers & Accessories", "cat_1": "Desktop Computers", "cat_2": "Desktop PC", "modelid": 124504851558, "date_crawled": "20220826", "item_name": "COMPUTER PACKAGE INTEL CORE 2 DUO DELL 2GB 160GB HDD WITH 17 INCHES FREE HEADSET AND MOUSEPAD", "url": "https://shopee.ph/COMPUTER-PACKAGE-INTEL-CORE-2-DUO-DELL-2GB-160GB-HDD-WITH-17-INCHES-FREE-HEADSET-AND-MOUSEPAD-i.359393740.8598186694", "shopid": "359393740", "itemid": "8598186694", "model_itemid": "8598186694", "sale_price": 1999.0, "item_price": 1999.0, "high_price": 4899.0, "brand": "", "item_rating": 4.69, "item_rating_count": 118.0, "product group": "GAS WATER HEATERS", "unique_name": "GWH", "country": "ID", "seller_name": "t5corp", "seller_rating": 4.615909, "seller_follower_count": 6905, "shopee_verified": false, "is_preferred_plus_seller": false, "is_official_shop": false, "item_desc": "SPECIFICATION:\n\n\u2705Processor: EDEX X2-U4200 \n\u2705Ram: 2gb RAM \n\u2705Storage: 16gb HDD\n\u2705Chrome9 HD GPI\n\u270519\" LCD SQ White Monitor\n\u2705Keyboard & Mouse\n\u2705Mousepad\n\u2705Cords included\n\u27051 Month warranty store replacement\n\u2705SHOPEE LINK:", "orig_price": 0.0, "stock": 601, "historical_sold": 289, "sold": 25, "model_count": 12, "model_stock": 9, "model_name": "SET 2GB / WIFI READY", "model_orig_price": 0.0, "model_sale_price": 3249.0, "final_price": 3249.0, "model_sold": 0, "total_model_sold": 0, "voucher_discount": 300.0, "model_contribution": 0.014975041597337771, "sales_units": 0, "warranty": "1 Month", "show_original_guarantee": false}, {"cat_0": "Computers & Accessories", "cat_1": "Desktop Computers", "cat_2": "Desktop PC", "modelid": 134616961910, "date_crawled": "20220826", "item_name": "COMPUTER PACKAGE INTEL CORE 2 DUO DELL 2GB 160GB HDD WITH 17 INCHES FREE HEADSET AND MOUSEPAD", "url": "https://shopee.ph/COMPUTER-PACKAGE-INTEL-CORE-2-DUO-DELL-2GB-160GB-HDD-WITH-17-INCHES-FREE-HEADSET-AND-MOUSEPAD-i.359393740.8598186694", "shopid": "359393740", "itemid": "8598186694", "model_itemid": "8598186694", "sale_price": 1999.0, "item_price": 1999.0, "high_price": 4899.0, "brand": "", "item_rating": 4.69, "item_rating_count": 118.0, "product group": "GAS WATER HEATERS", "unique_name": "GWH", "country": "ID", "seller_name": "t5corp", "seller_rating": 4.615909, "seller_follower_count": 6905, "shopee_verified": false, "is_preferred_plus_seller": false, "is_official_shop": false, "item_desc": "SPECIFICATION:\n\n\u2705Processor: EDEX X2-U4200 \n\u2705Ram: 2gb RAM \n\u2705Storage: 16gb HDD\n\u2705Chrome9 HD GPI\n\u270519\" LCD SQ White Monitor\n\u2705Keyboard & Mouse\n\u2705Mousepad\n\u2705Cords included\n\u27051 Month warranty store replacement\n\u2705SHOPEE LINK:", "orig_price": 0.0, "stock": 601, "historical_sold": 289, "sold": 25, "model_count": 12, "model_stock": 100, "model_name": "SET 22 INCH 4GB WIFI", "model_orig_price": 0.0, "model_sale_price": 4899.0, "final_price": 4899.0, "model_sold": 0, "total_model_sold": 0, "voucher_discount": 300.0, "model_contribution": 0.16638935108153077, "sales_units": 4, "warranty": "1 Month", "show_original_guarantee": false}, {"cat_0": "Computers & Accessories", "cat_1": "Desktop Computers", "cat_2": "Desktop PC", "modelid": 105657454949, "date_crawled": "20220826", "item_name": "COMPUTER PACKAGE INTEL CORE 2 DUO DELL 2GB 160GB HDD WITH 17 INCHES FREE HEADSET AND MOUSEPAD", "url": "https://shopee.ph/COMPUTER-PACKAGE-INTEL-CORE-2-DUO-DELL-2GB-160GB-HDD-WITH-17-INCHES-FREE-HEADSET-AND-MOUSEPAD-i.359393740.8598186694", "shopid": "359393740", "itemid": "8598186694", "model_itemid": "8598186694", "sale_price": 1999.0, "item_price": 1999.0, "high_price": 4899.0, "brand": "", "item_rating": 4.69, "item_rating_count": 118.0, "product group": "GAS WATER HEATERS", "unique_name": "GWH", "country": "ID", "seller_name": "t5corp", "seller_rating": 4.615909, "seller_follower_count": 6905, "shopee_verified": false, "is_preferred_plus_seller": false, "is_official_shop": false, "item_desc": "SPECIFICATION:\n\n\u2705Processor: EDEX X2-U4200 \n\u2705Ram: 2gb RAM \n\u2705Storage: 16gb HDD\n\u2705Chrome9 HD GPI\n\u270519\" LCD SQ White Monitor\n\u2705Keyboard & Mouse\n\u2705Mousepad\n\u2705Cords included\n\u27051 Month warranty store replacement\n\u2705SHOPEE LINK:", "orig_price": 0.0, "stock": 601, "historical_sold": 289, "sold": 25, "model_count": 12, "model_stock": 58, "model_name": "4GB  WIFI READY SET", "model_orig_price": 0.0, "model_sale_price": 4499.0, "final_price": 4499.0, "model_sold": 0, "total_model_sold": 0, "voucher_discount": 300.0, "model_contribution": 0.09650582362728785, "sales_units": 2, "warranty": "1 Month", "show_original_guarantee": false}, {"cat_0": "Computers & Accessories", "cat_1": "Desktop Computers", "cat_2": "Desktop PC", "modelid": 152178056828, "date_crawled": "20220826", "item_name": "COMPUTER PACKAGE INTEL CORE 2 DUO DELL 2GB 160GB HDD WITH 17 INCHES FREE HEADSET AND MOUSEPAD", "url": "https://shopee.ph/COMPUTER-PACKAGE-INTEL-CORE-2-DUO-DELL-2GB-160GB-HDD-WITH-17-INCHES-FREE-HEADSET-AND-MOUSEPAD-i.359393740.8598186694", "shopid": "359393740", "itemid": "8598186694", "model_itemid": "8598186694", "sale_price": 1999.0, "item_price": 1999.0, "high_price": 4899.0, "brand": "", "item_rating": 4.69, "item_rating_count": 118.0, "product group": "GAS WATER HEATERS", "unique_name": "GWH", "country": "ID", "seller_name": "t5corp", "seller_rating": 4.615909, "seller_follower_count": 6905, "shopee_verified": false, "is_preferred_plus_seller": false, "is_official_shop": false, "item_desc": "SPECIFICATION:\n\n\u2705Processor: EDEX X2-U4200 \n\u2705Ram: 2gb RAM \n\u2705Storage: 16gb HDD\n\u2705Chrome9 HD GPI\n\u270519\" LCD SQ White Monitor\n\u2705Keyboard & Mouse\n\u2705Mousepad\n\u2705Cords included\n\u27051 Month warranty store replacement\n\u2705SHOPEE LINK:", "orig_price": 0.0, "stock": 601, "historical_sold": 289, "sold": 25, "model_count": 12, "model_stock": 43, "model_name": "2GB 160GB STORAGE", "model_orig_price": 0.0, "model_sale_price": 2999.0, "final_price": 2999.0, "model_sold": 0, "total_model_sold": 0, "voucher_discount": 300.0, "model_contribution": 0.07154742096505824, "sales_units": 2, "warranty": "1 Month", "show_original_guarantee": false}, {"cat_0": "Computers & Accessories", "cat_1": "Desktop Computers", "cat_2": "Desktop PC", "modelid": 163540301245, "date_crawled": "20220826", "item_name": "COMPUTER PACKAGE INTEL CORE 2 DUO DELL 2GB 160GB HDD WITH 17 INCHES FREE HEADSET AND MOUSEPAD", "url": "https://shopee.ph/COMPUTER-PACKAGE-INTEL-CORE-2-DUO-DELL-2GB-160GB-HDD-WITH-17-INCHES-FREE-HEADSET-AND-MOUSEPAD-i.359393740.8598186694", "shopid": "359393740", "itemid": "8598186694", "model_itemid": "8598186694", "sale_price": 1999.0, "item_price": 1999.0, "high_price": 4899.0, "brand": "", "item_rating": 4.69, "item_rating_count": 118.0, "product group": "GAS WATER HEATERS", "unique_name": "GWH", "country": "ID", "seller_name": "t5corp", "seller_rating": 4.615909, "seller_follower_count": 6905, "shopee_verified": false, "is_preferred_plus_seller": false, "is_official_shop": false, "item_desc": "SPECIFICATION:\n\n\u2705Processor: EDEX X2-U4200 \n\u2705Ram: 2gb RAM \n\u2705Storage: 16gb HDD\n\u2705Chrome9 HD GPI\n\u270519\" LCD SQ White Monitor\n\u2705Keyboard & Mouse\n\u2705Mousepad\n\u2705Cords included\n\u27051 Month warranty store replacement\n\u2705SHOPEE LINK:", "orig_price": 0.0, "stock": 601, "historical_sold": 289, "sold": 25, "model_count": 12, "model_stock": 93, "model_name": "4GB 500GB STORAGE", "model_orig_price": 0.0, "model_sale_price": 3799.0, "final_price": 3799.0, "model_sold": 0, "total_model_sold": 0, "voucher_discount": 300.0, "model_contribution": 0.15474209650582363, "sales_units": 4, "warranty": "1 Month", "show_original_guarantee": false}, {"cat_0": "Computers & Accessories", "cat_1": "Desktop Computers", "cat_2": "Desktop PC", "modelid": 173687114563, "date_crawled": "20220826", "item_name": "COMPUTER PACKAGE INTEL CORE 2 DUO DELL 2GB 160GB HDD WITH 17 INCHES FREE HEADSET AND MOUSEPAD", "url": "https://shopee.ph/COMPUTER-PACKAGE-INTEL-CORE-2-DUO-DELL-2GB-160GB-HDD-WITH-17-INCHES-FREE-HEADSET-AND-MOUSEPAD-i.359393740.8598186694", "shopid": "359393740", "itemid": "8598186694", "model_itemid": "8598186694", "sale_price": 1999.0, "item_price": 1999.0, "high_price": 4899.0, "brand": "", "item_rating": 4.69, "item_rating_count": 118.0, "product group": "GAS WATER HEATERS", "unique_name": "GWH", "country": "ID", "seller_name": "t5corp", "seller_rating": 4.615909, "seller_follower_count": 6905, "shopee_verified": false, "is_preferred_plus_seller": false, "is_official_shop": false, "item_desc": "SPECIFICATION:\n\n\u2705Processor: EDEX X2-U4200 \n\u2705Ram: 2gb RAM \n\u2705Storage: 16gb HDD\n\u2705Chrome9 HD GPI\n\u270519\" LCD SQ White Monitor\n\u2705Keyboard & Mouse\n\u2705Mousepad\n\u2705Cords included\n\u27051 Month warranty store replacement\n\u2705SHOPEE LINK:", "orig_price": 0.0, "stock": 601, "historical_sold": 289, "sold": 25, "model_count": 12, "model_stock": 19, "model_name": "8GB 160GB STORAGE", "model_orig_price": 0.0, "model_sale_price": 4199.0, "final_price": 4199.0, "model_sold": 0, "total_model_sold": 0, "voucher_discount": 300.0, "model_contribution": 0.03161397670549085, "sales_units": 1, "warranty": "1 Month", "show_original_guarantee": false}, {"cat_0": "Computers & Accessories", "cat_1": "Desktop Computers", "cat_2": "Desktop PC", "modelid": 170783404923, "date_crawled": "20220826", "item_name": "COMPUTER PACKAGE INTEL CORE 2 DUO DELL 2GB 160GB HDD WITH 17 INCHES FREE HEADSET AND MOUSEPAD", "url": "https://shopee.ph/COMPUTER-PACKAGE-INTEL-CORE-2-DUO-DELL-2GB-160GB-HDD-WITH-17-INCHES-FREE-HEADSET-AND-MOUSEPAD-i.359393740.8598186694", "shopid": "359393740", "itemid": "8598186694", "model_itemid": "8598186694", "sale_price": 1999.0, "item_price": 1999.0, "high_price": 4899.0, "brand": "", "item_rating": 4.69, "item_rating_count": 118.0, "product group": "GAS WATER HEATERS", "unique_name": "GWH", "country": "ID", "seller_name": "t5corp", "seller_rating": 4.615909, "seller_follower_count": 6905, "shopee_verified": false, "is_preferred_plus_seller": false, "is_official_shop": false, "item_desc": "SPECIFICATION:\n\n\u2705Processor: EDEX X2-U4200 \n\u2705Ram: 2gb RAM \n\u2705Storage: 16gb HDD\n\u2705Chrome9 HD GPI\n\u270519\" LCD SQ White Monitor\n\u2705Keyboard & Mouse\n\u2705Mousepad\n\u2705Cords included\n\u27051 Month warranty store replacement\n\u2705SHOPEE LINK:", "orig_price": 0.0, "stock": 601, "historical_sold": 289, "sold": 25, "model_count": 12, "model_stock": 50, "model_name": "CPU WIFI READY", "model_orig_price": 0.0, "model_sale_price": 2249.0, "final_price": 2249.0, "model_sold": 0, "total_model_sold": 0, "voucher_discount": 300.0, "model_contribution": 0.08319467554076539, "sales_units": 2, "warranty": "1 Month", "show_original_guarantee": false}, {"cat_0": "Computers & Accessories", "cat_1": "Desktop Computers", "cat_2": "Desktop PC", "modelid": 181034239691, "date_crawled": "20220826", "item_name": "COMPUTER PACKAGE INTEL CORE 2 DUO DELL 2GB 160GB HDD WITH 17 INCHES FREE HEADSET AND MOUSEPAD", "url": "https://shopee.ph/COMPUTER-PACKAGE-INTEL-CORE-2-DUO-DELL-2GB-160GB-HDD-WITH-17-INCHES-FREE-HEADSET-AND-MOUSEPAD-i.359393740.8598186694", "shopid": "359393740", "itemid": "8598186694", "model_itemid": "8598186694", "sale_price": 1999.0, "item_price": 1999.0, "high_price": 4899.0, "brand": "", "item_rating": 4.69, "item_rating_count": 118.0, "product group": "GAS WATER HEATERS", "unique_name": "GWH", "country": "ID", "seller_name": "t5corp", "seller_rating": 4.615909, "seller_follower_count": 6905, "shopee_verified": false, "is_preferred_plus_seller": false, "is_official_shop": false, "item_desc": "SPECIFICATION:\n\n\u2705Processor: EDEX X2-U4200 \n\u2705Ram: 2gb RAM \n\u2705Storage: 16gb HDD\n\u2705Chrome9 HD GPI\n\u270519\" LCD SQ White Monitor\n\u2705Keyboard & Mouse\n\u2705Mousepad\n\u2705Cords included\n\u27051 Month warranty store replacement\n\u2705SHOPEE LINK:", "orig_price": 0.0, "stock": 601, "historical_sold": 289, "sold": 25, "model_count": 12, "model_stock": 91, "model_name": "4GB 160GB STORAGE", "model_orig_price": 0.0, "model_sale_price": 3399.0, "final_price": 3399.0, "model_sold": 0, "total_model_sold": 0, "voucher_discount": 300.0, "model_contribution": 0.15141430948419302, "sales_units": 4, "warranty": "1 Month", "show_original_guarantee": false}, {"cat_0": "Computers & Accessories", "cat_1": "Desktop Computers", "cat_2": "Desktop PC", "modelid": 152848747511, "date_crawled": "20220826", "item_name": "COMPUTER PACKAGE INTEL CORE 2 DUO DELL 2GB 160GB HDD WITH 17 INCHES FREE HEADSET AND MOUSEPAD", "url": "https://shopee.ph/COMPUTER-PACKAGE-INTEL-CORE-2-DUO-DELL-2GB-160GB-HDD-WITH-17-INCHES-FREE-HEADSET-AND-MOUSEPAD-i.359393740.8598186694", "shopid": "359393740", "itemid": "8598186694", "model_itemid": "8598186694", "sale_price": 1999.0, "item_price": 1999.0, "high_price": 4899.0, "brand": "", "item_rating": 4.69, "item_rating_count": 118.0, "product group": "GAS WATER HEATERS", "unique_name": "GWH", "country": "ID", "seller_name": "t5corp", "seller_rating": 4.615909, "seller_follower_count": 6905, "shopee_verified": false, "is_preferred_plus_seller": false, "is_official_shop": false, "item_desc": "SPECIFICATION:\n\n\u2705Processor: EDEX X2-U4200 \n\u2705Ram: 2gb RAM \n\u2705Storage: 16gb HDD\n\u2705Chrome9 HD GPI\n\u270519\" LCD SQ White Monitor\n\u2705Keyboard & Mouse\n\u2705Mousepad\n\u2705Cords included\n\u27051 Month warranty store replacement\n\u2705SHOPEE LINK:", "orig_price": 0.0, "stock": 601, "historical_sold": 289, "sold": 25, "model_count": 12, "model_stock": 49, "model_name": "SYSTEM UNIT ONLY", "model_orig_price": 0.0, "model_sale_price": 1999.0, "final_price": 1999.0, "model_sold": 0, "total_model_sold": 0, "voucher_discount": 300.0, "model_contribution": 0.08153078202995008, "sales_units": 2, "warranty": "1 Month", "show_original_guarantee": false}, {"cat_0": "Computers & Accessories", "cat_1": "Desktop Computers", "cat_2": "Desktop PC", "modelid": 170804887955, "date_crawled": "20220826", "item_name": "COMPUTER PACKAGE INTEL CORE 2 DUO DELL 2GB 160GB HDD WITH 17 INCHES FREE HEADSET AND MOUSEPAD", "url": "https://shopee.ph/COMPUTER-PACKAGE-INTEL-CORE-2-DUO-DELL-2GB-160GB-HDD-WITH-17-INCHES-FREE-HEADSET-AND-MOUSEPAD-i.359393740.8598186694", "shopid": "359393740", "itemid": "8598186694", "model_itemid": "8598186694", "sale_price": 1999.0, "item_price": 1999.0, "high_price": 4899.0, "brand": "", "item_rating": 4.69, "item_rating_count": 118.0, "product group": "GAS WATER HEATERS", "unique_name": "GWH", "country": "ID", "seller_name": "t5corp", "seller_rating": 4.615909, "seller_follower_count": 6905, "shopee_verified": false, "is_preferred_plus_seller": false, "is_official_shop": false, "item_desc": "SPECIFICATION:\n\n\u2705Processor: EDEX X2-U4200 \n\u2705Ram: 2gb RAM \n\u2705Storage: 16gb HDD\n\u2705Chrome9 HD GPI\n\u270519\" LCD SQ White Monitor\n\u2705Keyboard & Mouse\n\u2705Mousepad\n\u2705Cords included\n\u27051 Month warranty store replacement\n\u2705SHOPEE LINK:", "orig_price": 0.0, "stock": 601, "historical_sold": 289, "sold": 25, "model_count": 12, "model_stock": 23, "model_name": "SET CAM / WIFI READY", "model_orig_price": 0.0, "model_sale_price": 3499.0, "final_price": 3499.0, "model_sold": 0, "total_model_sold": 0, "voucher_discount": 300.0, "model_contribution": 0.03826955074875208, "sales_units": 1, "warranty": "1 Month", "show_original_guarantee": false}, {"cat_0": "Computers & Accessories", "cat_1": "Desktop Computers", "cat_2": "Desktop PC", "modelid": 124504851560, "date_crawled": "20220826", "item_name": "COMPUTER PACKAGE INTEL CORE 2 DUO DELL 2GB 160GB HDD WITH 17 INCHES FREE HEADSET AND MOUSEPAD", "url": "https://shopee.ph/COMPUTER-PACKAGE-INTEL-CORE-2-DUO-DELL-2GB-160GB-HDD-WITH-17-INCHES-FREE-HEADSET-AND-MOUSEPAD-i.359393740.8598186694", "shopid": "359393740", "itemid": "8598186694", "model_itemid": "8598186694", "sale_price": 1999.0, "item_price": 1999.0, "high_price": 4899.0, "brand": "", "item_rating": 4.69, "item_rating_count": 118.0, "product group": "GAS WATER HEATERS", "unique_name": "GWH", "country": "ID", "seller_name": "t5corp", "seller_rating": 4.615909, "seller_follower_count": 6905, "shopee_verified": false, "is_preferred_plus_seller": false, "is_official_shop": false, "item_desc": "SPECIFICATION:\n\n\u2705Processor: EDEX X2-U4200 \n\u2705Ram: 2gb RAM \n\u2705Storage: 16gb HDD\n\u2705Chrome9 HD GPI\n\u270519\" LCD SQ White Monitor\n\u2705Keyboard & Mouse\n\u2705Mousepad\n\u2705Cords included\n\u27051 Month warranty store replacement\n\u2705SHOPEE LINK:", "orig_price": 0.0, "stock": 601, "historical_sold": 289, "sold": 25, "model_count": 12, "model_stock": 47, "model_name": "WIFI READY & HEADSET", "model_orig_price": 0.0, "model_sale_price": 3999.0, "final_price": 3999.0, "model_sold": 0, "total_model_sold": 0, "voucher_discount": 300.0, "model_contribution": 0.07820299500831947, "sales_units": 2, "warranty": "1 Month", "show_original_guarantee": false}]