{"date_crawled": "20220826", "item_name": "Kulkas Sharp 2 pintu SJ-195MD No Frost", "url": "https://shopee.co.id/Kulkas-Sharp-2-pintu-SJ-195MD-No-Frost-i.85152735.1694288514", "shopid": "85152735", "itemid": "1694288514", "model_itemid": "1694288514", "sale_price": 2650000.0, "item_price": 2650000.0, "high_price": 2650000.0, "brand": "Sharp", "item_rating": 4.92, "item_rating_count": 83.0, "product group": "COOLING", "unique_name": "REF", "country": "ID", "seller_name": "princess_electronic", "seller_rating": 4.910456, "seller_follower_count": 4643, "shopee_verified": true, "is_preferred_plus_seller": false, "is_official_shop": false}