[{"cat_0": "Sepeda Motor", "cat_1": "Suku Cadang Motor", "cat_2": "Suku Cadang Motor Lainnya", "modelid": 40489059553, "date_crawled": "20220826", "item_name": "TEMPAT OLI SAMPING RX KING RXK RXZ RGR RXS", "url": "https://shopee.co.id/TEMPAT-OLI-SAMPING-RX-KING-RXK-RXZ-RGR-RXS-i.133189450.6117821344", "shopid": "133189450", "itemid": "6117821344", "model_itemid": "6117821344", "sale_price": 167000.0, "item_price": 167000.0, "high_price": 167000.0, "brand": "Tidak Ada Merek", "item_rating": 4.63, "item_rating_count": 73.0, "product group": "ENGINE OILS MOTOR CYCLES", "unique_name": "MCO", "country": "ID", "seller_name": "rmsknalpot", "seller_rating": 4.654416, "seller_follower_count": 459, "shopee_verified": true, "is_preferred_plus_seller": false, "is_official_shop": false, "item_desc": "MATERIALS FULL CHROME KINCLONG.. \n\n\nBARANG YANG KAMI JUAL READY STOK GAN !!!!\n\nPantau terus lapak kami, ada DISKON khusus setiap hari\n\nPEMESANAN\nUntuk Pemesanan yang dikonfirmasi sebelum jam 16.00 WIB dusahakan dikirim di hari yang sama bila memungkinkan :)\n\nhari minggu libur tidak ada pengiriman\n\nharap cantumkan nama motor dan warna produk saat order, tidak mencantumkan warna akan dikirim random\n\nResi :\n\nPenginputan Resi paling lama 2x24 Jam\n\njadwal input resi jam 08.30 ke esokan harinya. karna paket kami berangkatkan sore hari setelah kantor official kami tutup 17.00 wib.\n\nmohon tidak Spam pertanyaan mengenai Resi, karena pasti diinput\n\nJika Resi tidak bisa di Track, coba lagi pada 1x 24 jam seteleah di input.\n\nSELAMAT BERBELANJA RIA.\n\nTERIMAKASIH.", "orig_price": 180000.0, "stock": 943, "historical_sold": 103, "sold": 5, "model_count": 1, "model_stock": 943, "model_name": "", "model_orig_price": 180000.0, "model_sale_price": 167000.0, "final_price": 167000.0, "model_sold": 0, "total_model_sold": 0, "voucher_discount": "", "model_contribution": 1.0, "sales_units": 5, "warranty": null, "show_original_guarantee": false}]