{"date_crawled": "20220826", "item_name": "Ecohome slow juicer Tipe ESJ 999 Garansi resmi 1 tahun", "url": "https://shopee.co.id/Ecohome-slow-juicer-Tipe-ESJ-999-Garansi-resmi-1-tahun-i.168731078.9802520494", "shopid": "168731078", "itemid": "9802520494", "model_itemid": "9802520494", "sale_price": 1405530.0, "item_price": 1405530.0, "high_price": 1405530.0, "brand": "", "item_rating": 4.92, "item_rating_count": 59.0, "product group": "FOODPREPARATION", "unique_name": "FP1", "country": "ID", "seller_name": "hscanderson", "seller_rating": 4.925186, "seller_follower_count": 19703, "shopee_verified": true, "is_preferred_plus_seller": true, "is_official_shop": false}