{"date_crawled": "20220826", "item_name": "AC 1/2 PK AQUA KCR 5 AHP Low Voltage Super Cool Series", "url": "https://shopee.co.id/AC-1-2-PK-AQUA-KCR-5-AHP-Low-Voltage-Super-Cool-Series-i.255927582.15160477954", "shopid": "255927582", "itemid": "15160477954", "model_itemid": "15160477954", "sale_price": 2850000.0, "item_price": 2850000.0, "high_price": 3300000.0, "brand": "", "item_rating": 5.0, "item_rating_count": 3.0, "product group": "AIR CONDITIONER", "unique_name": "AIR", "country": "ID", "seller_name": "widola", "seller_rating": 4.977053, "seller_follower_count": 1393, "shopee_verified": true, "is_preferred_plus_seller": false, "is_official_shop": false}