{"date_crawled": "20220826", "item_name": "Digital earth Tester 4105 Kyoritsu / Meger Grounding meger tanah kyoritsu 4105", "url": "https://shopee.co.id/Digital-earth-Tester-4105-Kyoritsu-Meger-Grounding-meger-tanah-kyoritsu-4105-i.39018508.6656685637", "shopid": "39018508", "itemid": "6656685637", "model_itemid": "6656685637", "sale_price": 3399999.0, "item_price": 3399999.0, "high_price": 3399999.0, "brand": "", "item_rating": 5.0, "item_rating_count": 11.0, "product group": "AIR CONDITIONER", "unique_name": "AIR", "country": "ID", "seller_name": "lisnacung", "seller_rating": 4.864641, "seller_follower_count": 4958, "shopee_verified": true, "is_preferred_plus_seller": true, "is_official_shop": false}