{"date_crawled": "20220826", "item_name": "Food Processor Signora (no cubic cutter) FREE GIFT", "url": "https://shopee.co.id/Food-Processor-Signora-(no-cubic-cutter)-FREE-GIFT-i.85857077.9741846549", "shopid": "85857077", "itemid": "9741846549", "model_itemid": "9741846549", "sale_price": 1780000.0, "item_price": 1780000.0, "high_price": 1780000.0, "brand": "", "item_rating": 5.0, "item_rating_count": 1.0, "product group": "FOODPREPARATION", "unique_name": "FP2", "country": "ID", "seller_name": "elecstore_77", "seller_rating": 4.912644, "seller_follower_count": 647, "shopee_verified": false, "is_preferred_plus_seller": false, "is_official_shop": false}