{"date_crawled": "20220826", "item_name": "Gas Smoke House SERAFIM SSGSH-7 ( Mesin Pengasap Daging )", "url": "https://shopee.co.id/Gas-Smoke-House-SERAFIM-SSGSH-7-(-Mesin-Pengasap-Daging-)-i.61580810.8912675361", "shopid": "61580810", "itemid": "8912675361", "model_itemid": "8912675361", "sale_price": 4500000.0, "item_price": 4500000.0, "high_price": 4625000.0, "brand": "", "item_rating": 5.0, "item_rating_count": 5.0, "product group": "FOODPREPARATION", "unique_name": "FP2", "country": "ID", "seller_name": "chitramajujayaabadi", "seller_rating": 4.856964, "seller_follower_count": 985, "shopee_verified": true, "is_preferred_plus_seller": false, "is_official_shop": false}