{"date_crawled": "20220826", "item_name": "FOOD PROCESSOR PRO SIGNORA", "url": "https://shopee.co.id/FOOD-PROCESSOR-PRO-SIGNORA-i.59403612.4137101898", "shopid": "59403612", "itemid": "4137101898", "model_itemid": "4137101898", "sale_price": 1880000.0, "item_price": 1880000.0, "high_price": 2580000.0, "brand": "Signora", "item_rating": 5.0, "item_rating_count": 1.0, "product group": "FOODPREPARATION", "unique_name": "FP2", "country": "ID", "seller_name": "tintin_goodbakeware", "seller_rating": 4.929873, "seller_follower_count": 44314, "shopee_verified": true, "is_preferred_plus_seller": false, "is_official_shop": false}