{"date_crawled": "20220826", "item_name": "CELEBRAT A24 HEADPHONE WIRELESS HEADSET BLUETOOTH DENGAN EXTRA BASS SUARA JERNIH", "url": "https://shopee.co.id/CELEBRAT-A24-HEADPHONE-WIRELESS-HEADSET-BLUETOOTH-DENGAN-EXTRA-BASS-SUARA-JERNIH-i.171938281.8411786098", "shopid": "171938281", "itemid": "8411786098", "model_itemid": "8411786098", "sale_price": 350000.0, "item_price": 350000.0, "high_price": 350000.0, "brand": "Tidak Ada Merek", "item_rating": 4.93, "item_rating_count": 14.0, "product group": "HEADPHONES", "unique_name": "HPH", "country": "ID", "seller_name": "spotlite_official", "seller_rating": 4.718354, "seller_follower_count": 1385, "shopee_verified": false, "is_preferred_plus_seller": false, "is_official_shop": false}