{"date_crawled": "20220826", "item_name": "Behringer HPX2000 HPX 2000 Headphone DJ Studio Monitoring Recording Mixing Mastering Live Reference", "url": "https://shopee.co.id/Behringer-HPX2000-HPX-2000-Headphone-DJ-Studio-Monitoring-Recording-Mixing-Mastering-Live-Reference-i.295455465.4165710071", "shopid": "295455465", "itemid": "4165710071", "model_itemid": "4165710071", "sale_price": 375000.0, "item_price": 375000.0, "high_price": 375000.0, "brand": "Behringer", "item_rating": 5.0, "item_rating_count": 9.0, "product group": "HEADPHONES", "unique_name": "HPH", "country": "ID", "seller_name": "prosoundhub", "seller_rating": 4.879593, "seller_follower_count": 594, "shopee_verified": true, "is_preferred_plus_seller": false, "is_official_shop": false}