{"date_crawled": "20220826", "item_name": "PC GAMING EDITING CORE I5 MONITOR 19 INC", "url": "https://shopee.co.id/PC-GAMING-EDITING-CORE-I5-MONITOR-19-INC-i.380571261.13051755732", "shopid": "380571261", "itemid": "13051755732", "model_itemid": "13051755732", "sale_price": 3925000.0, "item_price": 3925000.0, "high_price": 3925000.0, "brand": "", "item_rating": 5.0, "item_rating_count": 4.0, "product group": "DESK COMPUT.ID", "unique_name": "DPC", "country": "ID", "seller_name": "mitracomputer12", "seller_rating": 4.872222, "seller_follower_count": 778, "shopee_verified": true, "is_preferred_plus_seller": true, "is_official_shop": false}