{"date_crawled": "20220826", "item_name": "GTA V PC GAMING AMD ATHLON 200GE (Ryzen Family) RAM 8GB SSD 120GB GRATIS ONGKIR", "url": "https://shopee.co.id/GTA-V-PC-GAMING-AMD-ATHLON-200GE-(Ryzen-Family)-RAM-8GB-SSD-120GB-GRATIS-ONGKIR-i.317009810.6055293327", "shopid": "317009810", "itemid": "6055293327", "model_itemid": "6055293327", "sale_price": 4299000.0, "item_price": 4299000.0, "high_price": 4299000.0, "brand": "", "item_rating": 5.0, "item_rating_count": 33.0, "product group": "DESK COMPUT.ID", "unique_name": "DPC", "country": "ID", "seller_name": "mastercomputermedan", "seller_rating": 4.935103, "seller_follower_count": 2487, "shopee_verified": false, "is_preferred_plus_seller": false, "is_official_shop": false}