{"date_crawled": "20220826", "item_name": "CPU PC GAMING RYZEN 5 5600G WITH RADEON VEGA 11 HDD 1TB SSD 120gb", "url": "https://shopee.co.id/CPU-PC-GAMING-RYZEN-5-5600G-WITH-RADEON-VEGA-11-HDD-1TB-SSD-120gb-i.13670583.1569077749", "shopid": "13670583", "itemid": "1569077749", "model_itemid": "1569077749", "sale_price": 6050000.0, "item_price": 6050000.0, "high_price": 6050000.0, "brand": "", "item_rating": 5.0, "item_rating_count": 5.0, "product group": "DESK COMPUT.ID", "unique_name": "DPC", "country": "ID", "seller_name": "putrinov0386", "seller_rating": 4.862365, "seller_follower_count": 8745, "shopee_verified": true, "is_preferred_plus_seller": true, "is_official_shop": false}