{"date_crawled": "20220826", "item_name": "Komputer Core i5 3470+SSD+HDD+VGA 2GB GDDR5+Monitor 19in waide", "url": "https://shopee.co.id/Komputer-Core-i5-3470-SSD-HDD-VGA-2GB-GDDR5-Monitor-19in-waide-i.254050011.17455982116", "shopid": "254050011", "itemid": "17455982116", "model_itemid": "17455982116", "sale_price": 4200000.0, "item_price": 4200000.0, "high_price": 4200000.0, "brand": "", "item_rating": 4.5, "item_rating_count": 2.0, "product group": "DESK COMPUT.ID", "unique_name": "DPC", "country": "ID", "seller_name": "aricomedi99", "seller_rating": 4.836957, "seller_follower_count": 302, "shopee_verified": false, "is_preferred_plus_seller": false, "is_official_shop": false}